LICENSE
MANIFEST.in
README.md
requirements.txt
setup.py
pyflubber/__init__.py
pyflubber/__version__.py
pyflubber/closed.py
pyflubber/interpolate.py
pyflubber/open.py
pyflubber/points.py
pyflubber.egg-info/PKG-INFO
pyflubber.egg-info/SOURCES.txt
pyflubber.egg-info/dependency_links.txt
pyflubber.egg-info/requires.txt
pyflubber.egg-info/top_level.txt