Metadata-Version: 2.1
Name: pyflubber
Version: 0.1.2
Summary: UNKNOWN
Home-page: https://github.com/maxme1/pyflubber
License: MIT
Download-URL: https://github.com/maxme1/pyflubber/v0.1.2.tar.gz
Keywords: interpolation,curves
Platform: UNKNOWN
Classifier: Development Status :: 5 - Production/Stable
Classifier: Programming Language :: Python :: 3.4
Classifier: Programming Language :: Python :: 3.5
Classifier: Programming Language :: Python :: 3.6
Classifier: Programming Language :: Python :: 3.7
Classifier: Programming Language :: Python :: 3.8
Classifier: Programming Language :: Python :: 3.9
